Metadata-Version: 1.1
Name: ipld
Version: 0.0.1
Summary: An IPLD implementation in Python
Home-page: UNKNOWN
Author: Tim Daubenschuetz
Author-email: tim.daubenschuetz@gmail.com
License: MIT License
Keywords: ipld python ipfs bigchaindb
Platform: UNKNOWN
Classifier: Development Status :: 3 - Alpha
Classifier: Intended Audience :: Developers
Classifier: Natural Language :: English
Classifier: License :: OSI Approved :: MIT License
Classifier: Programming Language :: Python :: 3 :: Only
Classifier: Programming Language :: Python :: 3.4
Classifier: Programming Language :: Python :: 3.5
Classifier: Topic :: Software Development
